localcartesian/_core.cpython-313-darwin.so
localcartesian/_core.pyi
localcartesian/__init__.py
localcartesian/py.typed
bin/Conformal3Proj
bin/CartConvert
bin/Planimeter
bin/Gravity
bin/TransverseMercatorProj
bin/IntersectTool
bin/Geod3Solve
bin/ConicProj
bin/RhumbSolve
bin/GeoidEval
bin/GeoConvert
bin/GeodSolve
bin/GeodesicProj
bin/Cart3Convert
bin/MagneticField
include/GeographicLib/LambertConformalConic.hpp
include/GeographicLib/MGRS.hpp
include/GeographicLib/LocalCartesian.hpp
include/GeographicLib/GeodesicLine.hpp
include/GeographicLib/GravityCircle.hpp
include/GeographicLib/UTMUPS.hpp
include/GeographicLib/Ellipsoid.hpp
include/GeographicLib/PolarStereographic.hpp
include/GeographicLib/AlbersEqualArea.hpp
include/GeographicLib/Utility.hpp
include/GeographicLib/MagneticModel.hpp
include/GeographicLib/SphericalHarmonic1.hpp
include/GeographicLib/TransverseMercator.hpp
include/GeographicLib/AuxAngle.hpp
include/GeographicLib/TransverseMercatorExact.hpp
include/GeographicLib/Config.h
include/GeographicLib/Angle.hpp
include/GeographicLib/SphericalHarmonic2.hpp
include/GeographicLib/Geoid.hpp
include/GeographicLib/Rhumb.hpp
include/GeographicLib/Trigfun.hpp
include/GeographicLib/SphericalHarmonic.hpp
include/GeographicLib/NormalGravity.hpp
include/GeographicLib/SphericalEngine.hpp
include/GeographicLib/GeodesicExact.hpp
include/GeographicLib/GARS.hpp
include/GeographicLib/Geocentric.hpp
include/GeographicLib/Accumulator.hpp
include/GeographicLib/PolygonArea.hpp
include/GeographicLib/Math.hpp
include/GeographicLib/Geodesic.hpp
include/GeographicLib/AzimuthalEquidistant.hpp
include/GeographicLib/Constants.hpp
include/GeographicLib/DST.hpp
include/GeographicLib/OSGB.hpp
include/GeographicLib/GeoCoords.hpp
include/GeographicLib/CassiniSoldner.hpp
include/GeographicLib/MagneticCircle.hpp
include/GeographicLib/NearestNeighbor.hpp
include/GeographicLib/AuxLatitude.hpp
include/GeographicLib/DMS.hpp
localcartesian-0.1.4.dist-info/RECORD
localcartesian-0.1.4.dist-info/WHEEL
localcartesian-0.1.4.dist-info/METADATA
localcartesian-0.1.4.dist-info/licenses/LICENSE
