Metadata-Version: 2.2
Name: localcartesian
Version: 0.1.4
Summary: Fast GPS to local Cartesian coordinate conversion using GeographicLib
Keywords: gps,coordinates,cartesian,geographic,geospatial
Author-Email: Daniel Pastor <danpasmor@gmail.com>, Cevat Ustun <custun@beyond.ai>
License: MIT
Classifier: Development Status :: 4 - Beta
Classifier: Intended Audience :: Developers
Classifier: Intended Audience :: Science/Research
Classifier: Operating System :: OS Independent
Classifier: Programming Language :: Python :: 3
Classifier: Programming Language :: Python :: 3.9
Classifier: Programming Language :: Python :: 3.10
Classifier: Programming Language :: Python :: 3.11
Classifier: Programming Language :: Python :: 3.12
Classifier: Programming Language :: Python :: 3.13
Classifier: Programming Language :: C++
Classifier: Topic :: Scientific/Engineering :: GIS
Requires-Python: >=3.9
Provides-Extra: dev
Requires-Dist: pytest>=7; extra == "dev"
Requires-Dist: ruff; extra == "dev"
Requires-Dist: mypy; extra == "dev"
Requires-Dist: cibuildwheel; extra == "dev"
Provides-Extra: test
Requires-Dist: pytest>=7.0; extra == "test"
Requires-Dist: numpy; extra == "test"
